{
    "id": "la-purga-relatos-de-lazarus-el-r",
    "name": "LA PURGA (relatos de Lázarus el renegado)",
    "shortName": "LA PURGA (relatos de Lázarus el renegado)",
    "installed": false,
    "summmary": "",
    "description": "ESCENARIO EN CASTELLANO CON HISTORIA. 1 JUGADOR\n\nSINOPSIS: Un pequeño grupo de fuerzas rebeldes, liderado por el comandante Lázarus, se dispone a destruír una instalación de investigación del Imperio y al Ultralisco que retienen en Taurenh3.\n\nPero no estarán solos en esta misión...\n\n",
    "author": "_ForgeUser10857499",
    "lastUpdated": "2013-03-28T18:55:27.000Z",
    "screenshots": [
        {}
    ],
    "patchNotes": [],
    "mods": [],
    "maps": []
}